LICENSE
aoc_solution_cli/aocgen.py
aoc_solution_cli/aocrun.py
aoc_solution_cli/recent_problem_saver.py
aoc_solution_cli-1.0.2.dist-info/LICENSE
aoc_solution_cli-1.0.2.dist-info/METADATA
aoc_solution_cli-1.0.2.dist-info/WHEEL
aoc_solution_cli-1.0.2.dist-info/entry_points.txt
aoc_solution_cli-1.0.2.dist-info/RECORD
