Metadata-Version: 2.1
Name: aoc-solution-cli
Version: 1.0.2
Summary: CLI for handling AoC solutions
License: LGPL-3.0-only
Author: taitep
Author-email: taitep@taitep.se
Requires-Python: >=3.12,<4.0
Classifier: License :: OSI Approved :: GNU Lesser General Public License v3 (LGPLv3)
Classifier: Programming Language :: Python :: 3
Classifier: Programming Language :: Python :: 3.12
Classifier: Programming Language :: Python :: 3.13
Requires-Dist: advent-of-code-data (>=2.0.1,<3.0.0)
Requires-Dist: click (>=8.1.7,<9.0.0)
